fundaml/__init__.py
fundaml/eda.py
fundaml/models.py
fundaml/scores.py
fundaml/tokenizers.py
fundaml/trainers.py
fundaml/transformer_from_scratch.py
fundaml-0.1.38.dist-info/LICENSE
fundaml-0.1.38.dist-info/METADATA
fundaml-0.1.38.dist-info/WHEEL
fundaml-0.1.38.dist-info/RECORD
