Metadata-Version: 2.1
Name: fundaml
Version: 0.1.38
Summary: A foundational machine learning library designed to streamline the end-to-end process of developing and deploying machine learning models. FundAML offers a broad array of tools and utilities for data preprocessing, model training, evaluation, and deployment, making it a fundamental solution for machine learning tasks.
License: MIT
Author: Tony Zoght
Requires-Python: >=3.10
Classifier: License :: OSI Approved :: MIT License
Classifier: Programming Language :: Python :: 3
Classifier: Programming Language :: Python :: 3.10
Classifier: Programming Language :: Python :: 3.11
Requires-Dist: numpy (>=1.24.0)
Requires-Dist: pandas (>=1.4.0)
Requires-Dist: torch (>=2.0.1,<3.0.0)
Requires-Dist: torchaudio (>=2.0.2,<3.0.0)
Requires-Dist: torchvision (>=0.15.2,<0.16.0)
